aliasr/__init__.py
aliasr/__main__.py
aliasr/app.py
aliasr/audit.py
aliasr/core/bootstrap.py
aliasr/core/cheats.py
aliasr/core/config.py
aliasr/core/creds.py
aliasr/core/globals.py
aliasr/core/inject.py
aliasr/core/list.py
aliasr/core/scan.py
aliasr/core/tmux.py
aliasr/core/variations.py
aliasr/data/config.toml
aliasr/data/cheats/variations.toml
aliasr/data/cheats/ad/active_directory.md
aliasr/data/cheats/ad/bloodhound.md
aliasr/data/cheats/ad/bloodyad.md
aliasr/data/cheats/ad/certipy.md
aliasr/data/cheats/ad/kerbrute.md
aliasr/data/cheats/ad/lsass.md
aliasr/data/cheats/ad/netexec.md
aliasr/data/cheats/ad/ntlm_theft.md
aliasr/data/cheats/ad/powerview.md
aliasr/data/cheats/ad/pygpoabuse.md
aliasr/data/cheats/ad/remote_execution.md
aliasr/data/cheats/ad/rpcclient.md
aliasr/data/cheats/ad/targetedkerberoast.md
aliasr/data/cheats/ad/impacket/impacket-kerberos.md
aliasr/data/cheats/ad/impacket/impacket-misc.md
aliasr/data/cheats/ad/impacket/ntlmrelayx.md
aliasr/data/cheats/ad/impacket/nxc-misc.md
aliasr/data/cheats/ad/impacket/secretsdump.md
aliasr/data/cheats/ad/techniques/coercion.md
aliasr/data/cheats/ad/techniques/relay.md
aliasr/data/cheats/cloud/aws/aws.md
aliasr/data/cheats/cloud/azure/aadinternals.md
aliasr/data/cheats/cloud/azure/azure.md
aliasr/data/cheats/cloud/gcp/gcp.md
aliasr/data/cheats/cracking/john.md
aliasr/data/cheats/linux/linux_privesc.md
aliasr/data/cheats/linux/utils/exiftool.md
aliasr/data/cheats/linux/utils/faketime.md
aliasr/data/cheats/linux/utils/grep.md
aliasr/data/cheats/linux/utils/keepass.md
aliasr/data/cheats/linux/utils/msfvenom.md
aliasr/data/cheats/linux/utils/openssl.md
aliasr/data/cheats/linux/utils/ssh-keygen.md
aliasr/data/cheats/linux/utils/sshpass.md
aliasr/data/cheats/linux/utils/username-anarchy.md
aliasr/data/cheats/misc/git.md
aliasr/data/cheats/misc/hackthebox.md
aliasr/data/cheats/misc/host_discovery.md
aliasr/data/cheats/protocols/dns.md
aliasr/data/cheats/protocols/ftp.md
aliasr/data/cheats/protocols/ldap.md
aliasr-1.0.0.dist-info/licenses/LICENSE
aliasr-1.0.0.dist-info/METADATA
aliasr-1.0.0.dist-info/WHEEL
aliasr-1.0.0.dist-info/entry_points.txt
aliasr-1.0.0.dist-info/top_level.txt
aliasr-1.0.0.dist-info/RECORD
