Metadata-Version: 2.4
Name: aliasr
Version: 1.0.0
Summary: Modern TUI launcher for pentest commands
Requires-Python: >=3.11
License-File: LICENSE
Requires-Dist: textual>=6.2.0
Requires-Dist: textual-autocomplete>=4.0.5
Requires-Dist: pykeepass>=4.0.0
Requires-Dist: pyperclip>=1.9.0
Dynamic: license-file
